sot/__about__.py
sot/__init__.py
sot/_app.py
sot/_helpers.py
sot/_process_utils.py
sot/blockchar_stream.py
sot/braille_stream.py
sot/bench/__init__.py
sot/bench/cli.py
sot/bench/core.py
sot/clean/__init__.py
sot/clean/cli.py
sot/disk/__init__.py
sot/disk/cli.py
sot/disk/disk_tui.py
sot/info/__init__.py
sot/info/cli.py
sot/info/logos.py
sot/ps/__init__.py
sot/ps/cli.py
sot/ps/ps_tui.py
sot/styles/app.tcss
sot/widgets/__init__.py
sot/widgets/base_widget.py
sot/widgets/confirmation_modal.py
sot/widgets/cpu.py
sot/widgets/disk.py
sot/widgets/health_score.py
sot/widgets/info.py
sot/widgets/memory.py
sot/widgets/network.py
sot/widgets/network_connections.py
sot/widgets/process_sorter.py
sot/widgets/processes.py
sot/widgets/sot.py
sot-6.0.1.data/data/share/man/man1/sot.1
sot-6.0.1.dist-info/METADATA
sot-6.0.1.dist-info/WHEEL
sot-6.0.1.dist-info/entry_points.txt
sot-6.0.1.dist-info/licenses/LICENSE
sot-6.0.1.dist-info/RECORD
