Metadata-Version: 2.4
Name: sot
Version: 6.0.1
Summary: System Oberving Tool
Project-URL: Code, https://github.com/anistark/sot
Project-URL: Issues, https://github.com/anistark/sot/issues
Project-URL: Homepage, https://github.com/anistark/sot
Project-URL: Documentation, https://github.com/anistark/sot#readme
Author-email: Kumar Anirudha <sot@anirudha.dev>
License-Expression: MIT
License-File: LICENSE
Keywords: cli,linux,monitor,system,tools
Classifier: Development Status :: 4 - Beta
Classifier: License :: OSI Approved :: MIT License
Classifier: Operating System :: MacOS
Classifier: Operating System :: POSIX :: Linux
Classifier: Programming Language :: Python
Classifier: Programming Language :: Python :: 3
Classifier: Programming Language :: Python :: 3.10
Classifier: Programming Language :: Python :: 3.11
Classifier: Programming Language :: Python :: 3.12
Classifier: Programming Language :: Python :: 3.13
Classifier: Topic :: Utilities
Requires-Python: >=3.10
Requires-Dist: distro>=1.9.0
Requires-Dist: psutil>=7.2.1
Requires-Dist: py-cpuinfo>=9.0.0
Requires-Dist: rich>=14.2.0
Requires-Dist: textual>=7.3.0
